odoo/addons/shopfloor_packing_info/README.rst
odoo/addons/shopfloor_packing_info/__init__.py
odoo/addons/shopfloor_packing_info/__manifest__.py
odoo/addons/shopfloor_packing_info/demo/shopfloor_packing_info_demo.xml
odoo/addons/shopfloor_packing_info/i18n/es_AR.po
odoo/addons/shopfloor_packing_info/i18n/shopfloor_packing_info.pot
odoo/addons/shopfloor_packing_info/models/__init__.py
odoo/addons/shopfloor_packing_info/models/res_partner.py
odoo/addons/shopfloor_packing_info/models/shopfloor_packing_info.py
odoo/addons/shopfloor_packing_info/models/stock_picking.py
odoo/addons/shopfloor_packing_info/models/stock_picking_type.py
odoo/addons/shopfloor_packing_info/readme/CONTRIBUTORS.rst
odoo/addons/shopfloor_packing_info/readme/DESCRIPTION.rst
odoo/addons/shopfloor_packing_info/security/ir.model.access.csv
odoo/addons/shopfloor_packing_info/services/__init__.py
odoo/addons/shopfloor_packing_info/services/checkout.py
odoo/addons/shopfloor_packing_info/static/description/icon.png
odoo/addons/shopfloor_packing_info/static/description/index.html
odoo/addons/shopfloor_packing_info/tests/__init__.py
odoo/addons/shopfloor_packing_info/tests/test_checkout_scan_line.py
odoo/addons/shopfloor_packing_info/tests/test_shopfloor_packing_info.py
odoo/addons/shopfloor_packing_info/views/menus.xml
odoo/addons/shopfloor_packing_info/views/res_partner_views.xml
odoo/addons/shopfloor_packing_info/views/shopfloor_packing_info_views.xml
odoo/addons/shopfloor_packing_info/views/stock_picking_type_views.xml
odoo/addons/shopfloor_packing_info/views/stock_picking_views.xml
odoo14_addon_shopfloor_packing_info-14.0.1.1.0.dist-info/METADATA
odoo14_addon_shopfloor_packing_info-14.0.1.1.0.dist-info/WHEEL
odoo14_addon_shopfloor_packing_info-14.0.1.1.0.dist-info/top_level.txt
odoo14_addon_shopfloor_packing_info-14.0.1.1.0.dist-info/RECORD
